pydbzengine/__init__.py
pydbzengine/airflow.py
pydbzengine/debeziumdlt.py
pydbzengine/helper.py
pydbzengine/install_libs.sh
pydbzengine/pom.xml
pydbzengine/config/log4j2.properties
pydbzengine/debezium/libs/activation-1.1.1.jar
pydbzengine/debezium/libs/antlr4-runtime-4.10.1.jar
pydbzengine/debezium/libs/aopalliance-repackaged-2.6.1.jar
pydbzengine/debezium/libs/bson-5.2.0.jar
pydbzengine/debezium/libs/bson-record-codec-5.2.0.jar
pydbzengine/debezium/libs/checker-qual-3.31.0.jar
pydbzengine/debezium/libs/commons-lang3-3.12.0.jar
pydbzengine/debezium/libs/connect-api-3.9.0.jar
pydbzengine/debezium/libs/connect-file-3.9.0.jar
pydbzengine/debezium/libs/connect-json-3.9.0.jar
pydbzengine/debezium/libs/connect-runtime-3.9.0.jar
pydbzengine/debezium/libs/connect-transforms-3.9.0.jar
pydbzengine/debezium/libs/debezium-api-3.1.1.Final.jar
pydbzengine/debezium/libs/debezium-connector-binlog-3.1.1.Final.jar
pydbzengine/debezium/libs/debezium-connector-mongodb-3.1.1.Final.jar
pydbzengine/debezium/libs/debezium-connector-mysql-3.1.1.Final.jar
pydbzengine/debezium/libs/debezium-connector-postgres-3.1.1.Final.jar
pydbzengine/debezium/libs/debezium-core-3.1.1.Final.jar
pydbzengine/debezium/libs/debezium-ddl-parser-3.1.1.Final.jar
pydbzengine/debezium/libs/debezium-embedded-3.1.1.Final.jar
pydbzengine/debezium/libs/debezium-sink-3.1.1.Final.jar
pydbzengine/debezium/libs/debezium-storage-file-3.1.1.Final.jar
pydbzengine/debezium/libs/debezium-storage-kafka-3.1.1.Final.jar
pydbzengine/debezium/libs/hk2-api-2.6.1.jar
pydbzengine/debezium/libs/hk2-locator-2.6.1.jar
pydbzengine/debezium/libs/hk2-utils-2.6.1.jar
pydbzengine/debezium/libs/jackson-annotations-2.16.2.jar
pydbzengine/debezium/libs/jackson-core-2.16.2.jar
pydbzengine/debezium/libs/jackson-databind-2.16.2.jar
pydbzengine/debezium/libs/jackson-datatype-jdk8-2.16.2.jar
pydbzengine/debezium/libs/jackson-datatype-jsr310-2.16.2.jar
pydbzengine/debezium/libs/jackson-jaxrs-base-2.16.2.jar
pydbzengine-3.1.1.0.dist-info/licenses/LICENSE
pydbzengine-3.1.1.0.dist-info/METADATA
pydbzengine-3.1.1.0.dist-info/WHEEL
pydbzengine-3.1.1.0.dist-info/top_level.txt
pydbzengine-3.1.1.0.dist-info/RECORD
