Metadata-Version: 2.4
Name: pydbzengine
Version: 3.1.1.0
Summary: Python Debezium Embedded Engine
Author: Memiiso Organization
License: Apache License 2.0
Project-URL: Homepage, https://github.com/memiiso/pydbzengine
Project-URL: Documentation, https://github.com/memiiso/pydbzengine
Project-URL: Repository, https://github.com/memiiso/pydbzengine
Keywords: Debezium,Replication,CDC
Classifier: Development Status :: 5 - Production/Stable
Classifier: Programming Language :: Python :: 3
Requires-Python: >=3.8
License-File: LICENSE
Requires-Dist: pyjnius==1.6.1
Requires-Dist: dlt>=1.5.0
Provides-Extra: dev
Requires-Dist: testcontainers>=4.9.1; extra == "dev"
Requires-Dist: dlt[duckdb]>=1.5.0; extra == "dev"
Requires-Dist: apache-airflow>=2.10.4; extra == "dev"
Dynamic: license-file
